odoo/addons/mrp_bom_widget_section_and_note_one2many/README.rst
odoo/addons/mrp_bom_widget_section_and_note_one2many/__init__.py
odoo/addons/mrp_bom_widget_section_and_note_one2many/__manifest__.py
odoo/addons/mrp_bom_widget_section_and_note_one2many/i18n/fr.po
odoo/addons/mrp_bom_widget_section_and_note_one2many/i18n/it.po
odoo/addons/mrp_bom_widget_section_and_note_one2many/i18n/mrp_bom_widget_section_and_note_one2many.pot
odoo/addons/mrp_bom_widget_section_and_note_one2many/models/__init__.py
odoo/addons/mrp_bom_widget_section_and_note_one2many/models/mrp_bom.py
odoo/addons/mrp_bom_widget_section_and_note_one2many/models/mrp_bom_line.py
odoo/addons/mrp_bom_widget_section_and_note_one2many/readme/CONTRIBUTORS.rst
odoo/addons/mrp_bom_widget_section_and_note_one2many/readme/CREDITS.rst
odoo/addons/mrp_bom_widget_section_and_note_one2many/readme/DESCRIPTION.rst
odoo/addons/mrp_bom_widget_section_and_note_one2many/readme/ROADMAP.rst
odoo/addons/mrp_bom_widget_section_and_note_one2many/readme/USAGE.rst
odoo/addons/mrp_bom_widget_section_and_note_one2many/static/description/icon.png
odoo/addons/mrp_bom_widget_section_and_note_one2many/static/description/index.html
odoo/addons/mrp_bom_widget_section_and_note_one2many/static/description/mrp_bom_widget_add_section_and_note.gif
odoo/addons/mrp_bom_widget_section_and_note_one2many/views/view_mrp_bom.xml
odoo12_addon_mrp_bom_widget_section_and_note_one2many-12.0.1.1.0.99.dev7.dist-info/METADATA
odoo12_addon_mrp_bom_widget_section_and_note_one2many-12.0.1.1.0.99.dev7.dist-info/WHEEL
odoo12_addon_mrp_bom_widget_section_and_note_one2many-12.0.1.1.0.99.dev7.dist-info/top_level.txt
odoo12_addon_mrp_bom_widget_section_and_note_one2many-12.0.1.1.0.99.dev7.dist-info/RECORD
