Metadata-Version: 2.1
Name: odoo12-addon-mrp_bom_widget_section_and_note_one2many
Version: 12.0.1.1.0.99.dev7
Summary: Add section and note in Bills of Materials
Home-page: https://github.com/OCA/manufacture
Author: GRAP,Odoo Community Association (OCA)
Author-email: support@odoo-community.org
License: AGPL-3
Classifier: Programming Language :: Python
Classifier: Framework :: Odoo
Classifier: Framework :: Odoo :: 12.0
Classifier: License :: OSI Approved :: GNU Affero General Public License v3
Requires-Python: >=3.5
Requires-Dist: odoo <12.1dev,>=12.0a
